neuro_helper/.DS_Store
neuro_helper/__init__.py
neuro_helper/colormap.py
neuro_helper/create_cortex.py
neuro_helper/dataframe.py
neuro_helper/generic.py
neuro_helper/map.py
neuro_helper/measurement.py
neuro_helper/plot.py
neuro_helper/rclone.py
neuro_helper/statistics.py
neuro_helper/storage.py
neuro_helper/__pycache__/__init__.cpython-38.pyc
neuro_helper/__pycache__/dataframe.cpython-38.pyc
neuro_helper/abstract/__init__.py
neuro_helper/abstract/map.py
neuro_helper/assets/.DS_Store
neuro_helper/assets/__init__.py
neuro_helper/assets/manager.py
neuro_helper/assets/hcp1200/.DS_Store
neuro_helper/assets/hcp1200/anat.midthickness.32k.L.surf.gii
neuro_helper/assets/hcp1200/anat.midthickness.32k.R.surf.gii
neuro_helper/assets/hcp1200/anat.midthickness.59k.L.surf.gii
neuro_helper/assets/hcp1200/anat.midthickness.59k.R.surf.gii
neuro_helper/assets/hcp1200/behaviour.csv
neuro_helper/assets/hcp1200/neighbors.59K.npy
neuro_helper/assets/hcp1200/template.cole.36012.32k.dlabel.nii
neuro_helper/assets/hcp1200/template.cole.36012.32k_cortex.dlabel.nii
neuro_helper/assets/hcp1200/template.cole.36012.4k_cortex.dlabel.nii
neuro_helper/assets/hcp1200/template.cole.36012.59k.dlabel.nii
neuro_helper/assets/hcp1200/template.cole.36012.59k_cortex.dlabel.nii
neuro_helper/assets/hcp1200/template.schaefer2018.20017.32k_cortex.dlabel.nii
neuro_helper/assets/hcp1200/template.schaefer2018.2007.32k_cortex.dlabel.nii
neuro_helper/assets/hcp1200/template.schaefer2018.2007.59k_cortex.dlabel.nii
neuro_helper/assets/hcp1200/template.wang2015.32k.dlabel.nii
neuro_helper/assets/hcp1200/template.wang2015.32k_cortex.dlabel.nii
neuro_helper/assets/hcp1200/template.wang2015.59k.dlabel.nii
neuro_helper/assets/hcp1200/template.wang2015.59k_cortex.dlabel.nii
neuro_helper/assets/hcp1200/topo.coord.32k.dscalar.nii
neuro_helper/assets/hcp1200/topo.coord.32k_cortex.dscalar.nii
neuro_helper/assets/hcp1200/topo.margulies2016.32k.dscalar.nii
neuro_helper/assets/hcp1200/topo.margulies2016.32k_cortex.dscalar.nii
neuro_helper-0.0.15.dist-info/LICENSE
neuro_helper-0.0.15.dist-info/METADATA
neuro_helper-0.0.15.dist-info/WHEEL
neuro_helper-0.0.15.dist-info/top_level.txt
neuro_helper-0.0.15.dist-info/RECORD
