Metadata-Version: 2.1
Name: neuro-helper
Version: 0.0.15
Summary: A simple package dealing with some analysis in my PhD thesis
Home-page: https://github.com/mehrshadg/neuro-data-helper
Author: Mehrshad Golesorkhi
Author-email: mehrshad.golesorkhi@gmail.com
License: UNKNOWN
Platform: UNKNOWN
Classifier: Programming Language :: Python :: 3
Classifier: License :: OSI Approved :: MIT License
Classifier: Operating System :: OS Independent
Requires-Python: >=3.6
